setup.py
submodfix/__init__.py
submodfix/submodfix.py
submodfix.egg-info/PKG-INFO
submodfix.egg-info/SOURCES.txt
submodfix.egg-info/dependency_links.txt
submodfix.egg-info/entry_points.txt
submodfix.egg-info/not-zip-safe
submodfix.egg-info/top_level.txt