Metadata-Version: 1.0
Name: submodfix
Version: 1.0
Summary: A tool to add submodules to a git repository from a .gitmodules file.
Home-page: http://submodfix.aj7may.com
Author: A.J. May
Author-email: UNKNOWN
License: Creative Commons Attribution-ShareAlike 3.0 Unported License
Platform: UNKNOWN
